chemistryai/__init__.py
chemistryai/chem_algo.py
chemistryai-0.2.4.dist-info/METADATA
chemistryai-0.2.4.dist-info/WHEEL
chemistryai-0.2.4.dist-info/top_level.txt
chemistryai-0.2.4.dist-info/RECORD
