Metadata-Version: 2.4
Name: chemistryai
Version: 0.2.4
Summary: chemistry library tailored for iit-jee
Home-page: https://github.com/infinity390/chemistryai
Author: education_is_self_done
Author-email: swastikmozumder@gmail.com
Classifier: Programming Language :: Python :: 3
Classifier: License :: OSI Approved :: MIT License
Classifier: Operating System :: OS Independent
Requires-Python: >=3.9
Requires-Dist: rdkit==2025.9.3
Requires-Dist: Pillow>=10.0.0
Dynamic: author
Dynamic: author-email
Dynamic: classifier
Dynamic: description
Dynamic: description-content-type
Dynamic: home-page
Dynamic: requires-dist
Dynamic: requires-python
Dynamic: summary
